README.md
setup.py
rlbot_legacy_gui/__init__.py
rlbot_legacy_gui/gui_agent.py
rlbot_legacy_gui/index_manager.py
rlbot_legacy_gui/mutator_editor.py
rlbot_legacy_gui/preset_editors.py
rlbot_legacy_gui/presets.py
rlbot_legacy_gui/qt_root.py
rlbot_legacy_gui.egg-info/PKG-INFO
rlbot_legacy_gui.egg-info/SOURCES.txt
rlbot_legacy_gui.egg-info/dependency_links.txt
rlbot_legacy_gui.egg-info/requires.txt
rlbot_legacy_gui.egg-info/top_level.txt
rlbot_legacy_gui/design/__init__.py
rlbot_legacy_gui/design/agent_customisation.py
rlbot_legacy_gui/design/agent_customisation.ui
rlbot_legacy_gui/design/car_customisation.py
rlbot_legacy_gui/design/car_customisation.ui
rlbot_legacy_gui/design/mutator_customisation.py
rlbot_legacy_gui/design/mutator_customisation.ui
rlbot_legacy_gui/design/qt_gui.py
rlbot_legacy_gui/design/qt_gui.ui