Metadata-Version: 2.1
Name: rlbot-legacy-gui
Version: 1.0.0
Summary: An old UI for RLBot built on PyQt5. Currently deprecated in favor of RLBotGUI.
Home-page: https://github.com/RLBot/RLBot
Author: RLBot Community
Author-email: rlbotofficial@gmail.com
License: MIT License
Keywords: rocket-league
Platform: UNKNOWN
Classifier: Programming Language :: Python :: 3
Classifier: License :: OSI Approved :: MIT License
Classifier: Operating System :: Microsoft :: Windows
